{
  "Airpush": [
    [
      "REFL:UNK._activity_pause",
      0.5774537324905396
    ],
    [
      "java.net.URL.openConnection",
      0.5647929310798645
    ],
    [
      "android.content.ContentValues.put",
      0.5448338389396667
    ],
    [
      "<UNK>",
      0.5398411154747009
    ],
    [
      "REFL:android.webkit.WebSettingsClassic.getUserAgentString",
      0.5307451486587524
    ],
    [
      "REFL:com.adobe.air.AndroidActivityWrapper.onContentChanged",
      0.5214241743087769
    ],
    [
      "android.webkit.WebView.setWebViewClient",
      0.5184418559074402
    ],
    [
      "REFL:UNK.getExternalStorageDirectory",
      0.5169373750686646
    ],
    [
      "libcore.io.IoBridge.open",
      0.5166361331939697
    ],
    [
      "android.app.SharedPreferencesImpl$EditorImpl.putString",
      0.5166310667991638
    ],
    [
      "android.app.ContextImpl.registerReceiver",
      0.5155815482139587
    ],
    [
      "REFL:com.android.internal.os.BatteryStatsImpl.getGlobalWifiRunningTime",
      0.5149078965187073
    ],
    [
      "android.telephony.TelephonyManager.getDeviceId",
      0.5123764872550964
    ],
    [
      "android.util.Base64.decode",
      0.5120007991790771
    ],
    [
      "REFL:com.android.internal.os.BatteryStatsImpl.getBluetoothOnTime",
      0.5010169744491577
    ]
  ],
  "DroidKungFu": [
    [
      "REFL:com.wqmobile.sdk.model.AppSettings.setNextADCount",
      0.5784684419631958
    ],
    [
      "REFL:com.baidu.android.pushservice.internal.CustomPushNotificationBuilder.writeObject",
      0.5586543679237366
    ],
    [
      "java.net.URL.openConnection",
      0.5440655946731567
    ],
    [
      "REFL:com.wqmobile.sdk.model.AppSettings.getIP",
      0.5440632700920105
    ],
    [
      "<UNK>",
      0.5370059609413147
    ],
    [
      "REFL:com.wqmobile.sdk.model.AppSettings.setLoopTimes",
      0.530758261680603
    ],
    [
      "android.webkit.WebView.setWebViewClient",
      0.5295367240905762
    ],
    [
      "REFL:com.adobe.air.AndroidActivityWrapper.onTitleChanged",
      0.5280591249465942
    ],
    [
      "REFL:com.wqmobile.sdk.model.AppSettings.setOfflineADCount",
      0.5262991189956665
    ],
    [
      "android.content.ContentValues.put",
      0.5247704386711121
    ],
    [
      "android.app.ContextImpl.registerReceiver",
      0.5184230804443359
    ],
    [
      "android.app.SharedPreferencesImpl$EditorImpl.putString",
      0.516886830329895
    ],
    [
      "REFL:com.adobe.air.AndroidActivityWrapper.onContentChanged",
      0.5102413296699524
    ],
    [
      "android.telephony.TelephonyManager.getDeviceId",
      0.49104318022727966
    ],
    [
      "REFL:UNK.getUidRxBytes",
      0.4879719614982605
    ]
  ],
  "Fusob": [
    [
      "android.telephony.TelephonyManager.getDeviceId",
      0.5747572183609009
    ],
    [
      "<UNK>",
      0.5715517401695251
    ],
    [
      "android.app.ContextImpl.registerReceiver",
      0.5533614158630371
    ],
    [
      "android.webkit.WebView.setWebViewClient",
      0.5272449851036072
    ],
    [
      "android.app.SharedPreferencesImpl$EditorImpl.putString",
      0.5244287848472595
    ],
    [
      "java.net.ProxySelectorImpl.select",
      0.5219597816467285
    ],
    [
      "libcore.io.IoBridge.open",
      0.5058115124702454
    ],
    [
      "android.util.Base64.decode",
      0.4993612468242645
    ],
    [
      "android.telephony.TelephonyManager.getLine1Number",
      0.46480587124824524
    ],
    [
      "java.io.File.exists",
      0.4613751769065857
    ],
    [
      "REFL:android.telephony.TelephonyManager.getDeviceId",
      0.4507441222667694
    ],
    [
      "android.app.ApplicationPackageManager.getInstalledPackages",
      0.4336085915565491
    ],
    [
      "android.os.SystemProperties.get",
      0.43091270327568054
    ],
    [
      "REFL:UNK.getCameraInfo",
      0.42197147011756897
    ],
    [
      "android.webkit.WebView.addJavascriptInterface",
      0.4156593978404999
    ]
  ],
  "Genpua": [
    [
      "REFL:com.google.appinventor.components.runtime.Label.FontItalic",
      0.5742027759552002
    ],
    [
      "java.net.URL.openConnection",
      0.562495231628418
    ],
    [
      "REFL:com.google.appinventor.components.runtime.Label.Width",
      0.5624707937240601
    ],
    [
      "REFL:com.google.appinventor.components.runtime.AdMob.AdUnitID",
      0.5618712306022644
    ],
    [
      "REFL:com.google.appinventor.components.runtime.Button.Text",
      0.5509001016616821
    ],
    [
      "android.content.ContentValues.put",
      0.544209361076355
    ],
    [
      "android.util.Base64.decode",
      0.5428941249847412
    ],
    [
      "libcore.io.IoBridge.open",
      0.5423349738121033
    ],
    [
      "REFL:com.google.appinventor.components.runtime.HorizontalArrangement.BackgroundColor",
      0.541674017906189
    ],
    [
      "REFL:UNK.getUidRxBytes",
      0.5415211915969849
    ],
    [
      "REFL:UNK.getTotalRxBytes",
      0.5410119295120239
    ],
    [
      "REFL:android.app.SharedPreferencesImpl$EditorImpl.apply",
      0.5397826433181763
    ],
    [
      "android.app.ContextImpl.registerReceiver",
      0.5393378138542175
    ],
    [
      "android.app.SharedPreferencesImpl$EditorImpl.putString",
      0.5345619320869446
    ],
    [
      "REFL:com.adobe.air.AndroidActivityWrapper.onContentChanged",
      0.5332300662994385
    ]
  ],
  "GinMaster": [
    [
      "REFL:com.wqmobile.sdk.model.AppSettings.getTextColor",
      0.5604995489120483
    ],
    [
      "REFL:com.adobe.air.AndroidActivityWrapper.onAttachedToWindow",
      0.5562383532524109
    ],
    [
      "REFL:com.adobe.air.AndroidActivityWrapper.onContentChanged",
      0.5548871159553528
    ],
    [
      "java.net.URL.openConnection",
      0.5530750155448914
    ],
    [
      "REFL:com.wqmobile.sdk.model.AppSettings.setNextADCount",
      0.5438022613525391
    ],
    [
      "android.app.ContextImpl.registerReceiver",
      0.530415415763855
    ],
    [
      "android.content.ContentValues.put",
      0.5282842516899109
    ],
    [
      "android.webkit.WebView.setWebViewClient",
      0.5274013876914978
    ],
    [
      "REFL:android.webkit.WebSettingsClassic.getUserAgentString",
      0.5249912738800049
    ],
    [
      "REFL:com.wqmobile.sdk.model.AppSettings.getIP",
      0.5237215161323547
    ],
    [
      "android.telephony.TelephonyManager.getDeviceId",
      0.5175748467445374
    ],
    [
      "REFL:com.alipay.mobile.common.logging.impl.TraceLoggerImpl.error",
      0.5172064304351807
    ],
    [
      "REFL:com.papaya.view.WebAlertDialog.setText",
      0.5153576135635376
    ],
    [
      "<UNK>",
      0.5086199641227722
    ],
    [
      "android.app.SharedPreferencesImpl$EditorImpl.putString",
      0.5079105496406555
    ]
  ],
  "Jisut": [
    [
      "libcore.io.IoBridge.open",
      0.4322848320007324
    ],
    [
      "java.io.File.exists",
      0.40127530694007874
    ],
    [
      "android.app.ActivityManager.getRunningTasks",
      0.37866830825805664
    ],
    [
      "android.os.SystemProperties.get",
      0.37785592675209045
    ],
    [
      "android.content.ContentResolver.query",
      0.37348389625549316
    ],
    [
      "android.app.SharedPreferencesImpl$EditorImpl.putInt",
      0.30951789021492004
    ],
    [
      "android.content.ContextWrapper.startActivity",
      0.2882956266403198
    ],
    [
      "android.content.ContextWrapper.startService",
      0.2639855444431305
    ],
    [
      "android.telephony.SmsManager.sendTextMessage",
      0.21622255444526672
    ],
    [
      "android.app.ActivityManager.killBackgroundProcesses",
      0.20255810022354126
    ],
    [
      "android.app.Activity.startActivity",
      0.1955060213804245
    ],
    [
      "java.lang.Runtime.exec",
      0.18164755403995514
    ]
  ],
  "Opfake": [
    [
      "REFL:ynlxcd.cwductjwjc.admyusbyfes.getClass",
      0.6402113437652588
    ],
    [
      "REFL:gvvwtjh.btvamydntnm.orkwplsket.getSystemService",
      0.5921106934547424
    ],
    [
      "REFL:android.app.SharedPreferencesImpl.edit",
      0.5848795771598816
    ],
    [
      "REFL:vbkoxh.cswnpr.vmbatqef.getClass",
      0.5789734721183777
    ],
    [
      "REFL:tp5x.WGt12.Y6Cg03N.loadAndDecode",
      0.5604575276374817
    ],
    [
      "<UNK>",
      0.5588268637657166
    ],
    [
      "android.app.SharedPreferencesImpl$EditorImpl.putString",
      0.5552582144737244
    ],
    [
      "REFL:android.app.AlarmManager.set",
      0.5549761056900024
    ],
    [
      "android.content.ContentValues.put",
      0.5479253530502319
    ],
    [
      "REFL:org.kxml2.io.KXmlParser.getAttributeName",
      0.5421571135520935
    ],
    [
      "REFL:libcore.net.url.JarURLConnectionImpl$JarURLConnectionInputStream.read",
      0.5420568585395813
    ],
    [
      "REFL:mejfudpoww.jieggdekc.sxeqdkxvvl.getSystemService",
      0.5367133617401123
    ],
    [
      "android.app.ContextImpl.registerReceiver",
      0.5277922749519348
    ],
    [
      "libcore.io.IoBridge.open",
      0.5274308919906616
    ],
    [
      "REFL:tp5x.WGt12.Y6Cg03N.showScreen",
      0.5258835554122925
    ]
  ],
  "SmsPay": [
    [
      "java.net.URL.openConnection",
      0.5684936046600342
    ],
    [
      "<UNK>",
      0.5558357238769531
    ],
    [
      "REFL:UNK.sendStaticMessage",
      0.5485770106315613
    ],
    [
      "REFL:android.app.ActivityManagerProxy.getMemoryInfo",
      0.5466449856758118
    ],
    [
      "REFL:java.net.PlainSocketImpl.getInputStream",
      0.5453700423240662
    ],
    [
      "android.util.Base64.decode",
      0.5437964200973511
    ],
    [
      "REFL:UNK.getUidRxBytes",
      0.5432251691818237
    ],
    [
      "android.content.ContentValues.put",
      0.541170597076416
    ],
    [
      "android.app.ContextImpl.registerReceiver",
      0.5369910597801208
    ],
    [
      "REFL:com.adobe.air.AndroidActivityWrapper.onContentChanged",
      0.5359171032905579
    ],
    [
      "android.webkit.WebView.setWebViewClient",
      0.5358224511146545
    ],
    [
      "libcore.io.IoBridge.open",
      0.5329441428184509
    ],
    [
      "android.app.SharedPreferencesImpl$EditorImpl.putString",
      0.5302073955535889
    ],
    [
      "android.telephony.TelephonyManager.getDeviceId",
      0.5222601294517517
    ],
    [
      "REFL:android.app.SharedPreferencesImpl$EditorImpl.apply",
      0.5204673409461975
    ]
  ]
}